[
	{
	 "2A - Buyer GSTIN": "06AABCB3524G1Z5",
	 "PR - Buyer GSTIN": "06AABCB3524G1Z5",
	 "QR - Buyer GSTIN": "06AABCB3524G1Z5",
	 "2B - Buyer GSTIN": "06AABCB3524G1Z5",
	 "2A - Seller GSTIN": "07AAECV7619K1ZV",
	 "PR - Seller GSTIN": "07AAECV7619K1ZV",
	 "QR - Seller GSTIN": "07AAECV7619K1ZV",
	 "2B - Seller GSTIN": "07AAECV7619K1ZV",
	 "2A vs PR - Total GST Difference": 20,
	 "2A vs QR - Total Amount Difference": 0,
	 "2A vs PR - Total Amount Difference": 0,
	 "QR vs PR - Total Amount Difference": 0,
	 "2A vs PR - Invoice Date Mismatch": "Match",
	 "2A vs QR - Invoice Date Mismatch": "Match",
	 "QR vs PR - Invoice Date Mismatch": "Match",
	 "2A vs PR - Invoice No Mismatch": "Match",
	 "2A vs QR - Invoice No Mismatch": "Match",
	 "QR vs PR - Invoice No Mismatch": "Match",
	 "QR - S3 Link": "https:\/\/hul-poc-invoices.s3.ap-south-1.amazonaws.com\/20042022HULIM\/20042022HULIM\/Uploaded%20Images_20.04.2022\/F028220000051421.tif",
	 "QR - Page Link": "https:\/\/s3-ap-south-1.amazonaws.com\/finkraftfiles\/March21-5-79.jpg",
	 "2A - IGST": 26460,
	 "2A - Total GST": 26460,
	 "2B - IGST": 26460,
	 "2B - Total GST": 26460,
	 "PR - IGST": 26460,
	 "PR - Total GST": 26460,
	 "2B - Filing Period": 102021,
	 "2A - Filing Period": 102021,
	 "2A - Invoice Date": "03\/10\/2021",
	 "PR - Invoice Date": "03\/10\/2021",
	 "QR - Invoice Date": "03\/10\/2021",
	 "2B - Invoice Date": "03\/10\/2021",
	 "QR - IRN Date": "09-15-2021",
	 "2A - IRN Date": "09-15-2021",
	 "2B - IRN Date": "09-15-2021",
	 "2A - Invoice Number": "VGT\/9573\/20-21",
	 "2B - Invoice Number": "VGT\/9573\/20-21",
	 "QR - Invoice Number": "VGT\/9573\/20-21",
	 "PR - Invoice Number": "VGT\/9573\/20-21",
	 "QR - IRN": "517bec8b5adff34211e2674de4fb73da67cec2381c3ebbd58836b153fafecab8",
	 "2A - Taxable": 147000,
	 "2A - Total Amount": 173460,
	 "QR - Total Amount": 173460,
	 "2B - Taxable": 147000,
	 "2B - Total Amount": 173460,
	 "PR - Taxable": 147000,
	 "PR - Total Amount": 173460,
	 "QR - Item Count": 1,
	 "QR - HSN Code": 995577,
	 "QR - NIC sign": "NIC",
	 "QR - Document Type": "INV"
	},
	{
	 "2A - Buyer GSTIN": "27AABCB3524G1Z1",
	 "PR - Buyer GSTIN": "27AABCB3524G1Z1",
	 "QR - Buyer GSTIN": "27AABCB3524G1Z1",
	 "2B - Buyer GSTIN": "27AABCB3524G1Z1",
	 "2A - Seller GSTIN": "27AABCM4781A1ZP",
	 "PR - Seller GSTIN": "27AABCM4781A1ZP",
	 "QR - Seller GSTIN": "27AABCM4781A1ZP",
	 "2B - Seller GSTIN": "27AABCM4781A1ZP",
	 "2A vs PR - Total GST Difference": 0,
	 "2A vs QR - Total Amount Difference": -938,
	 "2A vs PR - Total Amount Difference": -938,
	 "QR vs PR - Total Amount Difference": 0,
	 "2A vs PR - Invoice Date Mismatch": "Match",
	 "2A vs QR - Invoice Date Mismatch": "Match",
	 "QR vs PR - Invoice Date Mismatch": "Match",
	 "2A vs PR - Invoice No Mismatch": "Mismatch",
	 "2A vs QR - Invoice No Mismatch": "Match",
	 "QR vs PR - Invoice No Mismatch": "Mismatch",
	 "QR - S3 Link": "https:\/\/hul-poc-invoices.s3.ap-south-1.amazonaws.com\/31032022_abbott\/31032022_abbott\/1900384860_2020.pdf",
	 "QR - Page Link": "https:\/\/s3-ap-south-1.amazonaws.com\/finkraftfiles\/October20-7-50.jpg",
	 "2A - IGST": 1668,
	 "2A - Total GST": 1668,
	 "2B - IGST": 1668,
	 "2B - Total GST": 1668,
	 "PR - IGST": 1668,
	 "PR - Total GST": 1668,
	 "2B - Filing Period": 102021,
	 "2A - Filing Period": 102021,
	 "2A - Invoice Date": "10\/14\/2020",
	 "PR - Invoice Date": "10\/14\/2020",
	 "QR - Invoice Date": "10\/14\/2020",
	 "2B - Invoice Date": "10\/14\/2020",
	 "QR - IRN Date": "09-15-2021",
	 "2A - IRN Date": "09-15-2021",
	 "2B - IRN Date": "09-15-2021",
	 "2A - Invoice Number": "R50731563",
	 "2B - Invoice Number": "R50731563",
	 "QR - Invoice Number": "R50731563",
	 "PR - Invoice Number": "R-50731563",
	 "QR - IRN": "b62469e5018a412c256ba66686b45a7b6411fed19cd785f6204e508792c6d794",
	 "2A - Taxable": 9270,
	 "2A - Total Amount": 10000,
	 "QR - Total Amount": 10938,
	 "2B - Taxable": 9270,
	 "2B - Total Amount": 10938,
	 "PR - Taxable": 9270,
	 "PR - Total Amount": 10938,
	 "QR - Item Count": 3,
	 "QR - HSN Code": 995577,
	 "QR - NIC sign": "NIC",
	 "QR - Document Type": "INV"
	},
	{
	 "2A - Buyer GSTIN": "06AABCB3524G1Z5",
	 "PR - Buyer GSTIN": "06AABCB3524G1Z5",
	 "QR - Buyer GSTIN": "06AABCB3524G1Z5",
	 "2B - Buyer GSTIN": "06AABCB3524G1Z5",
	 "2A - Seller GSTIN": "06AABCK6665K1Z7",
	 "PR - Seller GSTIN": "06AABCK6665K1Z7",
	 "QR - Seller GSTIN": "06AABCK6665K1Z7",
	 "2B - Seller GSTIN": "06AABCK6665K1Z7",
	 "2A vs PR - Total GST Difference": 0,
	 "2A vs QR - Total Amount Difference": 0,
	 "2A vs PR - Total Amount Difference": -1,
	 "QR vs PR - Total Amount Difference": -1,
	 "2A vs PR - Invoice Date Mismatch": "Match",
	 "2A vs QR - Invoice Date Mismatch": "Match",
	 "QR vs PR - Invoice Date Mismatch": "Match",
	 "2A vs PR - Invoice No Mismatch": "Match",
	 "2A vs QR - Invoice No Mismatch": "Match",
	 "QR vs PR - Invoice No Mismatch": "Match",
	 "QR - S3 Link": "https:\/\/hul-poc-invoices.s3.ap-south-1.amazonaws.com\/31032022_abbott\/31032022_abbott\/1900384860_2020.pdf",
	 "QR - Page Link": "https:\/\/s3-ap-south-1.amazonaws.com\/finkraftfiles\/October20-2-66.jpg",
	 "2A - IGST": 12112,
	 "2A - Total GST": 12112,
	 "2B - IGST": 12112,
	 "2B - Total GST": 12112,
	 "PR - IGST": 12112,
	 "PR - Total GST": 12112,
	 "2B - Filing Period": 102021,
	 "2A - Filing Period": 102021,
	 "2A - Invoice Date": "10\/16\/2020",
	 "PR - Invoice Date": "10\/16\/2020",
	 "QR - Invoice Date": "10\/16\/2020",
	 "2B - Invoice Date": "10\/16\/2020",
	 "QR - IRN Date": "09-15-2021",
	 "2A - IRN Date": "09-15-2021",
	 "2B - IRN Date": "09-15-2021",
	 "2A - Invoice Number": "HRT20210000803",
	 "2B - Invoice Number": "HRT20210000803",
	 "QR - Invoice Number": "HRT20210000803",
	 "PR - Invoice Number": "HRT20210000803",
	 "QR - IRN": "2e5c8fd44ba0c02e4905cdb81844677487c7784ece6da1488ab65008cb40e9a",
	 "2A - Taxable": 67292,
	 "2A - Total Amount": 79404,
	 "QR - Total Amount": 79404,
	 "2B - Taxable": 67292,
	 "2B - Total Amount": 79404,
	 "PR - Taxable": 67293,
	 "PR - Total Amount": 79405,
	 "QR - Item Count": 2,
	 "QR - HSN Code": 995577,
	 "QR - NIC sign": "NIC",
	 "QR - Document Type": "INV"
	},
	{
	 "2A - Buyer GSTIN": "06AABCB3524G1Z5",
	 "PR - Buyer GSTIN": "06AABCB3524G1Z5",
	 "QR - Buyer GSTIN": "06AABCB3524G1Z5",
	 "2B - Buyer GSTIN": "06AABCB3524G1Z5",
	 "2A - Seller GSTIN": "06AABCK6665K1Z7",
	 "PR - Seller GSTIN": "06AABCK6665K1Z7",
	 "QR - Seller GSTIN": "06AABCK6665K1Z7",
	 "2B - Seller GSTIN": "06AABCK6665K1Z7",
	 "2A vs PR - Total GST Difference": 0,
	 "2A vs QR - Total Amount Difference": 0,
	 "2A vs PR - Total Amount Difference": 1,
	 "QR vs PR - Total Amount Difference": 1,
	 "2A vs PR - Invoice Date Mismatch": "Match",
	 "2A vs QR - Invoice Date Mismatch": "Match",
	 "QR vs PR - Invoice Date Mismatch": "Match",
	 "2A vs PR - Invoice No Mismatch": "Match",
	 "2A vs QR - Invoice No Mismatch": "Match",
	 "QR vs PR - Invoice No Mismatch": "Match",
	 "QR - S3 Link": "https:\/\/hul-poc-invoices.s3.ap-south-1.amazonaws.com\/31032022_abbott\/31032022_abbott\/1900384860_2020.pdf",
	 "QR - Page Link": "https:\/\/s3-ap-south-1.amazonaws.com\/finkraftfiles\/October20-2-64.jpg",
	 "2A - IGST": 5820,
	 "2A - Total GST": 5820,
	 "2B - IGST": 5820,
	 "2B - Total GST": 5820,
	 "PR - IGST": 5820,
	 "PR - Total GST": 5820,
	 "2A - Invoice Date": "10\/16\/2020",
	 "PR - Invoice Date": "10\/16\/2020",
	 "QR - Invoice Date": "10\/16\/2020",
	 "2B - Invoice Date": "10\/16\/2020",
	 "2A - Invoice Number": "HRT20210000806",
	 "2B - Invoice Number": "HRT20210000806",
	 "QR - Invoice Number": "HRT20210000806",
	 "PR - Invoice Number": "HRT20210000806",
	 "QR - IRN": "8989894fc96feedd8aa986c4e9254f3befdc74ce8fcfe7d15ccdlcbe8c34c8ef",
	 "2A - Taxable": 32330,
	 "2A - Total Amount": 38150,
	 "QR - Total Amount": 38150,
	 "2B - Taxable": 32330,
	 "2B - Total Amount": 38150,
	 "PR - Taxable": 32329,
	 "PR - Total Amount": 38149,
	 "QR - Item Count": 34,
	 "QR - HSN Code": 995577,
	 "QR - NIC sign": "NIC",
	 "QR - Document Type": "INV"
	},
	{
	 "2A - Buyer GSTIN": "06AABCB3524G1Z5",
	 "PR - Buyer GSTIN": "06AABCB3524G1Z5",
	 "QR - Buyer GSTIN": "06AABCB3524G1Z5",
	 "2B - Buyer GSTIN": "06AABCB3524G1Z5",
	 "2A - Seller GSTIN": "06AABCK6665K1Z7",
	 "PR - Seller GSTIN": "06AABCK6665K1Z7",
	 "QR - Seller GSTIN": "06AABCK6665K1Z7",
	 "2B - Seller GSTIN": "06AABCK6665K1Z7",
	 "2A vs PR - Total GST Difference": 0,
	 "2A vs QR - Total Amount Difference": 369576,
	 "2A vs PR - Total Amount Difference": 1,
	 "QR vs PR - Total Amount Difference": -369575,
	 "2A vs PR - Invoice Date Mismatch": "Match",
	 "2A vs QR - Invoice Date Mismatch": "Match",
	 "QR vs PR - Invoice Date Mismatch": "Match",
	 "2A vs PR - Invoice No Mismatch": "Match",
	 "2A vs QR - Invoice No Mismatch": "Match",
	 "QR vs PR - Invoice No Mismatch": "Match",
	 "QR - S3 Link": "https:\/\/hul-poc-invoices.s3.ap-south-1.amazonaws.com\/20042022HULIM\/20042022HULIM\/Uploaded%20Images_20.04.2022\/C006220000050623.tif",
	 "QR - Page Link": "https:\/\/s3-ap-south-1.amazonaws.com\/finkraftfiles\/October20-2-62.jpg",
	 "2A - IGST": 56946,
	 "2A - Total GST": 56946,
	 "2B - IGST": 56946,
	 "2B - Total GST": 56946,
	 "PR - IGST": 56946,
	 "PR - Total GST": 56946,
	 "2A - Invoice Date": "10\/16\/2020",
	 "PR - Invoice Date": "10\/16\/2020",
	 "QR - Invoice Date": "10\/16\/2020",
	 "2B - Invoice Date": "10\/16\/2020",
	 "2A - Invoice Number": "HRT20210000809",
	 "2B - Invoice Number": "HRT20210000809",
	 "QR - Invoice Number": "HRT20210000809",
	 "PR - Invoice Number": "HRT20210000809",
	 "QR - IRN": "ef430923944787t524d1d5e06559b939eb2c264134140262bac84d75o27dof",
	 "2A - Taxable": 316363,
	 "2A - Total Amount": 373309,
	 "QR - Total Amount": 3733,
	 "2B - Taxable": 316363,
	 "2B - Total Amount": 373309,
	 "PR - Taxable": 316362,
	 "PR - Total Amount": 373308,
	 "QR - Item Count": 35,
	 "QR - HSN Code": 995577,
	 "QR - NIC sign": "NIC",
	 "QR - Document Type": "INV"
	},
	{
	 "2A - Buyer GSTIN": "06AABCB3524G1Z5",
	 "PR - Buyer GSTIN": "06AABCB3524G1Z5",
	 "QR - Buyer GSTIN": "06AABCB3524G1Z5",
	 "2B - Buyer GSTIN": "06AABCB3524G1Z5",
	 "2A - Seller GSTIN": "06AABCK6665K1Z7",
	 "PR - Seller GSTIN": "06AABCK6665K1Z7",
	 "QR - Seller GSTIN": "06AABCK6665K1Z7",
	 "2B - Seller GSTIN": "06AABCK6665K1Z7",
	 "2A vs PR - Total GST Difference": -2,
	 "2A vs QR - Total Amount Difference": 0,
	 "2A vs PR - Total Amount Difference": 0,
	 "QR vs PR - Total Amount Difference": 0,
	 "2A vs PR - Invoice Date Mismatch": "Match",
	 "2A vs QR - Invoice Date Mismatch": "Match",
	 "QR vs PR - Invoice Date Mismatch": "Match",
	 "2A vs PR - Invoice No Mismatch": "Match",
	 "2A vs QR - Invoice No Mismatch": "Match",
	 "QR vs PR - Invoice No Mismatch": "Match",
	 "QR - S3 Link": "https:\/\/hul-poc-invoices.s3.ap-south-1.amazonaws.com\/20042022HULIM\/20042022HULIM\/Uploaded%20Images_20.04.2022\/C006220000050623.tif,https:\/\/hul-poc-invoices.s3.ap-south-1.amazonaws.com\/20042022HULIM\/20042022HULIM\/Uploaded%20Images_20.04.2022\/C006220000050623.tif",
	 "QR - Page Link": "https:\/\/s3-ap-south-1.amazonaws.com\/finkraftfiles\/March21-5-48.jpg",
	 "2A - IGST": 1684,
	 "2A - Total GST": 1684,
	 "2B - IGST": 1684,
	 "2B - Total GST": 1684,
	 "PR - IGST": 1686,
	 "PR - Total GST": 1686,
	 "2A - Invoice Date": "03\/12\/2021",
	 "PR - Invoice Date": "03\/12\/2021",
	 "QR - Invoice Date": "03\/12\/2021",
	 "2B - Invoice Date": "03\/12\/2021",
	 "2A - Invoice Number": "HRT20210001431",
	 "2B - Invoice Number": "HRT20210001431",
	 "QR - Invoice Number": "HRT20210001431",
	 "PR - Invoice Number": "HRT20210001431",
	 "QR - IRN": "0ad0d047c1105730224ffb24f6e6e9c61c98436870d4b5a24co8ffbed26006",
	 "2A - Taxable": 9366,
	 "2A - Total Amount": 11050,
	 "QR - Total Amount": 11050,
	 "2B - Taxable": 9366,
	 "2B - Total Amount": 11050,
	 "PR - Taxable": 9364,
	 "PR - Total Amount": 11050,
	 "QR - Item Count": 3,
	 "QR - HSN Code": 995577,
	 "QR - NIC sign": "NIC",
	 "QR - Document Type": "INV"
	},
	{
	 "2A - Buyer GSTIN": "27AABCB3524G1Z1",
	 "PR - Buyer GSTIN": "27AABCB3524G1Z1",
	 "QR - Buyer GSTIN": "27AABCB3524G1Z1",
	 "2B - Buyer GSTIN": "27AABCB3524G1Z1",
	 "2A - Seller GSTIN": "27AABCI3815M1ZF",
	 "PR - Seller GSTIN": "27AABCI3815M1ZF",
	 "QR - Seller GSTIN": "27AABCI3815M1ZF",
	 "2B - Seller GSTIN": "27AABCI3815M1ZF",
	 "2A vs PR - Total GST Difference": -2,
	 "2A vs QR - Total Amount Difference": 0,
	 "2A vs PR - Total Amount Difference": 0,
	 "QR vs PR - Total Amount Difference": 0,
	 "2A vs PR - Invoice Date Mismatch": "Mismatch",
	 "2A vs QR - Invoice Date Mismatch": "Mismatch",
	 "QR vs PR - Invoice Date Mismatch": "Match",
	 "2A vs PR - Invoice No Mismatch": "Mismatch",
	 "2A vs QR - Invoice No Mismatch": "Match",
	 "QR vs PR - Invoice No Mismatch": "Mismatch",
	 "QR - S3 Link": "https:\/\/qr-invoice.s3.ap-south-1.amazonaws.com\/CHA%20Invoices\/CHA%20Invoices\/2728.pdf",
	 "QR - Page Link": "https:\/\/s3-ap-south-1.amazonaws.com\/finkraftfiles\/March21-5-50.jpg",
	 "2A - IGST": 1936,
	 "2A - Total GST": 1936,
	 "2B - IGST": 1936,
	 "2B - Total GST": 1936,
	 "PR - IGST": 1938,
	 "PR - Total GST": 1938,
	 "2A - Invoice Date": "12-15-2021",
	 "PR - Invoice Date": "03\/12\/2021",
	 "QR - Invoice Date": "03\/12\/2021",
	 "2B - Invoice Date": "03\/12\/2021",
	 "2A - Invoice Number": "F\/20-21\/0036307",
	 "2B - Invoice Number": "F\/20-21\/0036307",
	 "QR - Invoice Number": "F\/20-21\/0036307",
	 "PR - Invoice Number": "F-20-21-0036307",
	 "QR - IRN": "5b24907787888ec0f6e607dd9lee37efe8661352225e7086478le4e2c294a6bd",
	 "2A - Taxable": 10763,
	 "2A - Total Amount": 12699,
	 "QR - Total Amount": 12699,
	 "2B - Taxable": 10763,
	 "2B - Total Amount": 12699,
	 "PR - Taxable": 10761,
	 "PR - Total Amount": 12699,
	 "QR - Item Count": 6,
	 "QR - HSN Code": 995577,
	 "QR - NIC sign": "NIC",
	 "QR - Document Type": "INV"
	},
	{
	 "2A - Buyer GSTIN": "06AABCB3524G1Z5",
	 "PR - Buyer GSTIN": "06AABCB3524G1Z5",
	 "QR - Buyer GSTIN": "06AABCB3524G1Z5",
	 "2B - Buyer GSTIN": "06AABCB3524G1Z5",
	 "2A - Seller GSTIN": "06AABCE4461B1Z6",
	 "PR - Seller GSTIN": "06AABCE4461B1Z6",
	 "QR - Seller GSTIN": "06AABCE4461B1Z6",
	 "2B - Seller GSTIN": "06AABCE4461B1Z6",
	 "2A vs PR - Total GST Difference": 0,
	 "2A vs QR - Total Amount Difference": 0,
	 "2A vs PR - Total Amount Difference": 0,
	 "QR vs PR - Total Amount Difference": 0,
	 "2A vs PR - Invoice Date Mismatch": "Match",
	 "2A vs QR - Invoice Date Mismatch": "Match",
	 "QR vs PR - Invoice Date Mismatch": "Match",
	 "2A vs PR - Invoice No Mismatch": "Match",
	 "2A vs QR - Invoice No Mismatch": "Match",
	 "QR vs PR - Invoice No Mismatch": "Match",
	 "QR - S3 Link": "https:\/\/hul-poc-invoices.s3.ap-south-1.amazonaws.com\/20042022HULIM\/20042022HULIM\/Uploaded%20Images_20.04.2022\/F026DD22S0047239.tif",
	 "QR - Page Link": "https:\/\/s3-ap-south-1.amazonaws.com\/finkraftfiles\/March21-5-27.jpg",
	 "2A - IGST": 187500,
	 "2A - Total GST": 187500,
	 "2B - IGST": 187500,
	 "2B - Total GST": 187500,
	 "PR - IGST": 187500,
	 "PR - Total GST": 187500,
	 "2A - Invoice Date": "03\/09\/2021",
	 "PR - Invoice Date": "03\/09\/2021",
	 "QR - Invoice Date": "03\/09\/2021",
	 "2B - Invoice Date": "03\/09\/2021",
	 "2A - Invoice Number": "B1Z6HR10352",
	 "2B - Invoice Number": "B1Z6HR10352",
	 "QR - Invoice Number": "B1Z6HR10352",
	 "PR - Invoice Number": "B1Z6HR10352",
	 "QR - IRN": "c858e6f73fdb5c150b58d4a2a04099d944ab3934fb326f3e8f1d014554046c89",
	 "2A - Taxable": 1041667,
	 "2A - Total Amount": 1229167,
	 "QR - Total Amount": 1229167,
	 "2B - Taxable": 1041667,
	 "2B - Total Amount": 1229167,
	 "PR - Taxable": 1041667,
	 "PR - Total Amount": 1229167,
	 "QR - Item Count": 4,
	 "QR - HSN Code": 995577,
	 "QR - NIC sign": "NIC",
	 "QR - Document Type": "INV"
	},
	{
	 "2A - Buyer GSTIN": "06AABCB3524G1Z5",
	 "PR - Buyer GSTIN": "06AABCB3524G1Z5",
	 "QR - Buyer GSTIN": "06AABCB3524G1Z5",
	 "2B - Buyer GSTIN": "06AABCB3524G1Z5",
	 "2A - Seller GSTIN": "06AABCE4461B1Z6",
	 "PR - Seller GSTIN": "06AABCE4461B1Z6",
	 "QR - Seller GSTIN": "06AABCE4461B1Z6",
	 "2B - Seller GSTIN": "06AABCE4461B1Z6",
	 "2A vs PR - Total GST Difference": 0,
	 "2A vs QR - Total Amount Difference": 0,
	 "2A vs PR - Total Amount Difference": 0,
	 "QR vs PR - Total Amount Difference": 0,
	 "2A vs PR - Invoice Date Mismatch": "Match",
	 "2A vs QR - Invoice Date Mismatch": "Match",
	 "QR vs PR - Invoice Date Mismatch": "Match",
	 "2A vs PR - Invoice No Mismatch": "Match",
	 "2A vs QR - Invoice No Mismatch": "Match",
	 "QR vs PR - Invoice No Mismatch": "Match",
	 "QR - S3 Link": "https:\/\/hul-poc-invoices.s3.ap-south-1.amazonaws.com\/31032022_abbott\/31032022_abbott\/5100158583_2021.pdf",
	 "QR - Page Link": "https:\/\/s3-ap-south-1.amazonaws.com\/finkraftfiles\/March21-5-29.jpg",
	 "2A - IGST": 187500,
	 "2A - Total GST": 187500,
	 "2B - IGST": 187500,
	 "2B - Total GST": 187500,
	 "PR - IGST": 187500,
	 "PR - Total GST": 187500,
	 "2A - Invoice Date": "03\/09\/2021",
	 "PR - Invoice Date": "03\/09\/2021",
	 "QR - Invoice Date": "03\/09\/2021",
	 "2B - Invoice Date": "03\/09\/2021",
	 "2A - Invoice Number": "B1Z6HR10351",
	 "2B - Invoice Number": "B1Z6HR10351",
	 "QR - Invoice Number": "B1Z6HR10351",
	 "PR - Invoice Number": "B1Z6HR10351",
	 "QR - IRN": "c858e6f73fdb5c150b58d4a2a04099d944ab3934fb326f3e8f1d014554046c89",
	 "2A - Taxable": 1041667,
	 "2A - Total Amount": 1229167,
	 "QR - Total Amount": 1229167,
	 "2B - Taxable": 1041667,
	 "2B - Total Amount": 1229167,
	 "PR - Taxable": 1041667,
	 "PR - Total Amount": 1229167,
	 "QR - Item Count": 1,
	 "QR - HSN Code": 995577,
	 "QR - NIC sign": "NIC",
	 "QR - Document Type": "INV"
	},
	{
	 "2A - Buyer GSTIN": "06AABCB3524G1Z5",
	 "PR - Buyer GSTIN": "06AABCB3524G1Z5",
	 "QR - Buyer GSTIN": "06AABCB3524G1Z5",
	 "2B - Buyer GSTIN": "06AABCB3524G1Z5",
	 "2A - Seller GSTIN": "06AABCE4461B1Z6",
	 "PR - Seller GSTIN": "06AABCE4461B1Z6",
	 "QR - Seller GSTIN": "06AABCE4461B1Z6",
	 "2B - Seller GSTIN": "06AABCE4461B1Z6",
	 "2A vs PR - Total GST Difference": 0,
	 "2A vs QR - Total Amount Difference": 0,
	 "2A vs PR - Total Amount Difference": 0,
	 "QR vs PR - Total Amount Difference": 0,
	 "2A vs PR - Invoice Date Mismatch": "Match",
	 "2A vs QR - Invoice Date Mismatch": "Match",
	 "QR vs PR - Invoice Date Mismatch": "Match",
	 "2A vs PR - Invoice No Mismatch": "Match",
	 "2A vs QR - Invoice No Mismatch": "Match",
	 "QR vs PR - Invoice No Mismatch": "Match",
	 "QR - S3 Link": "https:\/\/hul-poc-invoices.s3.ap-south-1.amazonaws.com\/31032022_abbott\/31032022_abbott\/1901019026-%201901019023.pdf",
	 "QR - Page Link": "https:\/\/s3-ap-south-1.amazonaws.com\/finkraftfiles\/October20-2-27.jpg",
	 "2A - IGST": 385920,
	 "2A - Total GST": 385920,
	 "2B - IGST": 385920,
	 "2B - Total GST": 385920,
	 "PR - IGST": 385920,
	 "PR - Total GST": 385920,
	 "2A - Invoice Date": "10\/26\/2020",
	 "PR - Invoice Date": "10\/26\/2020",
	 "QR - Invoice Date": "10\/26\/2020",
	 "2B - Invoice Date": "10\/26\/2020",
	 "2A - Invoice Number": "B1Z6HR9705",
	 "2B - Invoice Number": "B1Z6HR9705",
	 "QR - Invoice Number": "B1Z6HR9705",
	 "PR - Invoice Number": "B1Z6HR9705",
	 "QR - IRN": "2aa0d92dfe5cldfc36eb20124d23f0c7656d247e70b84bc6edbd48618602d376",
	 "2A - Taxable": 2144000,
	 "2A - Total Amount": 2529920,
	 "QR - Total Amount": 2529920,
	 "2B - Taxable": 2144000,
	 "2B - Total Amount": 2529920,
	 "PR - Taxable": 2144000,
	 "PR - Total Amount": 2529920,
	 "QR - Item Count": 3,
	 "QR - HSN Code": 995577,
	 "QR - NIC sign": "NIC",
	 "QR - Document Type": "INV"
	},
	{
	 "2A - Buyer GSTIN": "06AABCB3524G1Z5",
	 "PR - Buyer GSTIN": "06AABCB3524G1Z5",
	 "QR - Buyer GSTIN": "06AABCB3524G1Z5",
	 "2B - Buyer GSTIN": "06AABCB3524G1Z5",
	 "2A - Seller GSTIN": "06AAACC4175D1Z2",
	 "PR - Seller GSTIN": "06AAACC4175D1Z2",
	 "QR - Seller GSTIN": "06AAACC4175D1Z2",
	 "2B - Seller GSTIN": "06AAACC4175D1Z2",
	 "2A vs PR - Total GST Difference": -2,
	 "2A vs QR - Total Amount Difference": 0,
	 "2A vs PR - Total Amount Difference": 41507,
	 "QR vs PR - Total Amount Difference": 41507,
	 "2A vs PR - Invoice Date Mismatch": "Match",
	 "2A vs QR - Invoice Date Mismatch": "Match",
	 "QR vs PR - Invoice Date Mismatch": "Match",
	 "2A vs PR - Invoice No Mismatch": "Match",
	 "2A vs QR - Invoice No Mismatch": "Match",
	 "QR vs PR - Invoice No Mismatch": "Match",
	 "QR - S3 Link": "https:\/\/hul-poc-invoices.s3.ap-south-1.amazonaws.com\/31032022_abbott\/31032022_abbott\/1901019026-%201901019023.pdf",
	 "QR - Page Link": "https:\/\/s3-ap-south-1.amazonaws.com\/finkraftfiles\/March21-5-77.jpg",
	 "2A - IGST": 6940,
	 "2A - Total GST": 6940,
	 "2B - IGST": 6940,
	 "2B - Total GST": 6940,
	 "PR - IGST": 6942,
	 "PR - Total GST": 6942,
	 "2A - Invoice Date": "03\/07\/2021",
	 "PR - Invoice Date": "03\/07\/2021",
	 "QR - Invoice Date": "03\/07\/2021",
	 "2B - Invoice Date": "03\/07\/2021",
	 "2A - Invoice Number": "HRM2021000019322",
	 "2B - Invoice Number": "HRM2021000019322",
	 "QR - Invoice Number": "HRM2021000019322",
	 "PR - Invoice Number": "HRM2021000019322",
	 "QR - IRN": "919032033a8a9a8e0dc95cea3193818beeba2afda85ba2b65b3a8a1bf69dcf14",
	 "2A - Taxable": 38567,
	 "2A - Total Amount": 45507,
	 "QR - Total Amount": 45507,
	 "2B - Taxable": 38567,
	 "2B - Total Amount": 45507,
	 "PR - Taxable": 38565,
	 "PR - Total Amount": 4000,
	 "QR - Item Count": 4,
	 "QR - HSN Code": 995577,
	 "QR - NIC sign": "NIC",
	 "QR - Document Type": "INV"
	},
	{
	 "2A - Buyer GSTIN": "06AABCB3524G1Z5",
	 "PR - Buyer GSTIN": "06AABCB3524G1Z5",
	 "QR - Buyer GSTIN": "06AABCB3524G1Z5",
	 "2B - Buyer GSTIN": "06AABCB3524G1Z5",
	 "2A - Seller GSTIN": "06AAACC4175D1Z2",
	 "PR - Seller GSTIN": "06AAACC4175D1Z2",
	 "QR - Seller GSTIN": "06AAACC4175D1Z2",
	 "2B - Seller GSTIN": "06AAACC4175D1Z2",
	 "2A vs PR - Total GST Difference": -2,
	 "2A vs QR - Total Amount Difference": 0,
	 "2A vs PR - Total Amount Difference": 0,
	 "QR vs PR - Total Amount Difference": 0,
	 "2A vs PR - Invoice Date Mismatch": "Match",
	 "2A vs QR - Invoice Date Mismatch": "Match",
	 "QR vs PR - Invoice Date Mismatch": "Match",
	 "2A vs PR - Invoice No Mismatch": "Match",
	 "2A vs QR - Invoice No Mismatch": "Match",
	 "QR vs PR - Invoice No Mismatch": "Match",
	 "QR - S3 Link": "https:\/\/hul-poc-invoices.s3.ap-south-1.amazonaws.com\/31032022_abbott\/31032022_abbott\/1901019026-%201901019023.pdf",
	 "QR - Page Link": "https:\/\/s3-ap-south-1.amazonaws.com\/finkraftfiles\/March21-5-85.jpg",
	 "2A - IGST": 204,
	 "2A - Total GST": 204,
	 "2B - IGST": 204,
	 "2B - Total GST": 204,
	 "PR - IGST": 206,
	 "PR - Total GST": 206,
	 "2A - Invoice Date": "03\/07\/2021",
	 "PR - Invoice Date": "03\/07\/2021",
	 "QR - Invoice Date": "03\/07\/2021",
	 "2B - Invoice Date": "03\/07\/2021",
	 "2A - Invoice Number": "HRM2021000019311",
	 "2B - Invoice Number": "HRM2021000019311",
	 "QR - Invoice Number": "HRM2021000019311",
	 "PR - Invoice Number": "HRM2021000019311",
	 "QR - IRN": "4cdbd652020fc9457ccd33d4c26546b0800bd3e18e99106dec51adc53865c5e7",
	 "2A - Taxable": 1146,
	 "2A - Total Amount": 1350,
	 "QR - Total Amount": 1350,
	 "2B - Taxable": 1146,
	 "2B - Total Amount": 1350,
	 "PR - Taxable": 1144,
	 "PR - Total Amount": 1350,
	 "QR - Item Count": 645,
	 "QR - HSN Code": 995577,
	 "QR - NIC sign": "NIC",
	 "QR - Document Type": "INV"
	},
	{
	 "2A - Buyer GSTIN": "06AABCB3524G1Z5",
	 "PR - Buyer GSTIN": "06AABCB3524G1Z5",
	 "QR - Buyer GSTIN": "06AABCB3524G1Z5",
	 "2B - Buyer GSTIN": "06AABCB3524G1Z5",
	 "2A - Seller GSTIN": "06AAACC4175D1Z2",
	 "PR - Seller GSTIN": "06AAACC4175D1Z2",
	 "QR - Seller GSTIN": "06AAACC4175D1Z2",
	 "2B - Seller GSTIN": "06AAACC4175D1Z2",
	 "2A vs PR - Total GST Difference": 0,
	 "2A vs QR - Total Amount Difference": 0,
	 "2A vs PR - Total Amount Difference": 0,
	 "QR vs PR - Total Amount Difference": 0,
	 "2A vs PR - Invoice Date Mismatch": "Match",
	 "2A vs QR - Invoice Date Mismatch": "Match",
	 "QR vs PR - Invoice Date Mismatch": "Match",
	 "2A vs PR - Invoice No Mismatch": "Match",
	 "2A vs QR - Invoice No Mismatch": "Match",
	 "QR vs PR - Invoice No Mismatch": "Match",
	 "QR - S3 Link": "https:\/\/hul-poc-invoices.s3.ap-south-1.amazonaws.com\/31032022_abbott\/31032022_abbott\/1900384860_2020.pdf",
	 "QR - Page Link": "https:\/\/s3-ap-south-1.amazonaws.com\/finkraftfiles\/March21-5-34.jpg",
	 "2A - IGST": 66,
	 "2A - Total GST": 66,
	 "2B - IGST": 66,
	 "2B - Total GST": 66,
	 "PR - IGST": 66,
	 "PR - Total GST": 66,
	 "2A - Invoice Date": "03\/07\/2021",
	 "PR - Invoice Date": "03\/07\/2021",
	 "QR - Invoice Date": "03\/07\/2021",
	 "2B - Invoice Date": "03\/07\/2021",
	 "2A - Invoice Number": "HRM2021000019329",
	 "2B - Invoice Number": "HRM2021000019329",
	 "QR - Invoice Number": "HRM2021000019329",
	 "PR - Invoice Number": "HRM2021000019329",
	 "QR - IRN": "5b85e5ab8d279e891d97d99795537409df4e6969af47b16d4a601de4cc16886",
	 "2A - Taxable": 369,
	 "2A - Total Amount": 435,
	 "QR - Total Amount": 435,
	 "2B - Taxable": 369,
	 "2B - Total Amount": 435,
	 "PR - Taxable": 369,
	 "PR - Total Amount": 435,
	 "QR - Item Count": 45,
	 "QR - HSN Code": 995577,
	 "QR - NIC sign": "NIC",
	 "QR - Document Type": "INV"
	},
	{
	 "2A - Buyer GSTIN": "29AABCB3524G1ZX",
	 "PR - Buyer GSTIN": "29AABCB3524G1ZX",
	 "QR - Buyer GSTIN": "29AABCB3524G1ZX",
	 "2B - Buyer GSTIN": "29AABCB3524G1ZX",
	 "2A - Seller GSTIN": "29AAACC4175D1ZU",
	 "PR - Seller GSTIN": "29AAACC4175D1ZU",
	 "QR - Seller GSTIN": "29AAACC4175D1ZU",
	 "2B - Seller GSTIN": "29AAACC4175D1ZU",
	 "2A vs PR - Total GST Difference": 0,
	 "2A vs QR - Total Amount Difference": 0,
	 "2A vs PR - Total Amount Difference": 0,
	 "QR vs PR - Total Amount Difference": 0,
	 "2A vs PR - Invoice Date Mismatch": "Match",
	 "2A vs QR - Invoice Date Mismatch": "Match",
	 "QR vs PR - Invoice Date Mismatch": "Match",
	 "2A vs PR - Invoice No Mismatch": "Match",
	 "2A vs QR - Invoice No Mismatch": "Match",
	 "QR vs PR - Invoice No Mismatch": "Match",
	 "QR - S3 Link": "https:\/\/hul-poc-invoices.s3.ap-south-1.amazonaws.com\/31032022_abbott\/31032022_abbott\/1900384860_2020.pdf",
	 "QR - Page Link": "https:\/\/s3-ap-south-1.amazonaws.com\/finkraftfiles\/March21-5-42.jpg",
	 "2A - IGST": 2886,
	 "2A - Total GST": 2886,
	 "2B - IGST": 2886,
	 "2B - Total GST": 2886,
	 "PR - IGST": 2886,
	 "PR - Total GST": 2886,
	 "2A - Invoice Date": "03\/07\/2021",
	 "PR - Invoice Date": "03\/07\/2021",
	 "QR - Invoice Date": "03\/07\/2021",
	 "2B - Invoice Date": "03\/07\/2021",
	 "2A - Invoice Number": "KAS2021000041660",
	 "2B - Invoice Number": "KAS2021000041660",
	 "QR - Invoice Number": "KAS2021000041660",
	 "PR - Invoice Number": "KAS2021000041660",
	 "QR - IRN": "a02340177791285844356c1379620bbd71567b35396331486697e6a96292a8f",
	 "2A - Taxable": 16037,
	 "2A - Total Amount": 18923,
	 "QR - Total Amount": 18923,
	 "2B - Taxable": 16037,
	 "2B - Total Amount": 18923,
	 "PR - Taxable": 16037,
	 "PR - Total Amount": 18923,
	 "QR - Item Count": 5,
	 "QR - HSN Code": 995577,
	 "QR - NIC sign": "NIC",
	 "QR - Document Type": "INV"
	},
	{
	 "2A - Buyer GSTIN": "27AABCB3524G1Z1",
	 "PR - Buyer GSTIN": "27AABCB3524G1Z1",
	 "QR - Buyer GSTIN": "27AABCB3524G1Z1",
	 "2B - Buyer GSTIN": "27AABCB3524G1Z1",
	 "2A - Seller GSTIN": "27AAACC4175D1ZY",
	 "PR - Seller GSTIN": "27AAACC4175D1ZY",
	 "QR - Seller GSTIN": "27AAACC4175D1ZY",
	 "2B - Seller GSTIN": "27AAACC4175D1ZY",
	 "2A vs PR - Total GST Difference": -2,
	 "2A vs QR - Total Amount Difference": 0,
	 "2A vs PR - Total Amount Difference": 6492,
	 "QR vs PR - Total Amount Difference": 6492,
	 "2A vs PR - Invoice Date Mismatch": "Match",
	 "2A vs QR - Invoice Date Mismatch": "Match",
	 "QR vs PR - Invoice Date Mismatch": "Match",
	 "2A vs PR - Invoice No Mismatch": "Match",
	 "2A vs QR - Invoice No Mismatch": "Match",
	 "QR vs PR - Invoice No Mismatch": "Match",
	 "QR - S3 Link": "https:\/\/qr-invoice.s3.ap-south-1.amazonaws.com\/CHA%20Invoices\/2587.pdf",
	 "QR - Page Link": "https:\/\/s3-ap-south-1.amazonaws.com\/finkraftfiles\/March21-5-87.jpg",
	 "2A - IGST": 1294,
	 "2A - Total GST": 1294,
	 "2B - IGST": 1294,
	 "2B - Total GST": 1294,
	 "PR - IGST": 1296,
	 "PR - Total GST": 1296,
	 "2A - Invoice Date": "03\/06\/2021",
	 "PR - Invoice Date": "03\/06\/2021",
	 "QR - Invoice Date": "03\/06\/2021",
	 "2B - Invoice Date": "03\/06\/2021",
	 "2A - Invoice Number": "MHS2021000049422",
	 "2B - Invoice Number": "MHS2021000049422",
	 "QR - Invoice Number": "MHS2021000049422",
	 "PR - Invoice Number": "MHS2021000049422",
	 "QR - IRN": "e2ea036331da0e2c329c7678c16164207c7652b7bbc867ed6fb5f5dr951cea91",
	 "2A - Taxable": 7198,
	 "2A - Total Amount": 8492,
	 "QR - Total Amount": 8492,
	 "2B - Taxable": 7198,
	 "2B - Total Amount": 8492,
	 "PR - Taxable": 7196,
	 "PR - Total Amount": 2000,
	 "QR - Item Count": 6,
	 "QR - HSN Code": 995577,
	 "QR - NIC sign": "NIC",
	 "QR - Document Type": "INV"
	},
	{
	 "2A - Buyer GSTIN": "27AABCB3524G1Z1",
	 "PR - Buyer GSTIN": "27AABCB3524G1Z1",
	 "QR - Buyer GSTIN": "27AABCB3524G1Z112",
	 "2B - Buyer GSTIN": "27AABCB3524G1Z1",
	 "2A - Seller GSTIN": "27AAACC4175D1ZY",
	 "PR - Seller GSTIN": "27AAACC4175D1ZY",
	 "QR - Seller GSTIN": "27AAACC4175D1ZY",
	 "2B - Seller GSTIN": "27AAACC4175D1ZY",
	 "2A vs PR - Total GST Difference": 0,
	 "2A vs QR - Total Amount Difference": 0,
	 "2A vs PR - Total Amount Difference": 0,
	 "QR vs PR - Total Amount Difference": 0,
	 "2A vs PR - Invoice Date Mismatch": "Match",
	 "2A vs QR - Invoice Date Mismatch": "Match",
	 "QR vs PR - Invoice Date Mismatch": "Match",
	 "2A vs PR - Invoice No Mismatch": "Match",
	 "2A vs QR - Invoice No Mismatch": "Match",
	 "QR vs PR - Invoice No Mismatch": "Match",
	 "QR - S3 Link": "https:\/\/qr-invoice.s3.ap-south-1.amazonaws.com\/CHA%20Invoices\/2587.pdf",
	 "QR - Page Link": "https:\/\/s3-ap-south-1.amazonaws.com\/finkraftfiles\/March21-5-89.jpg",
	 "2A - IGST": 1482,
	 "2A - Total GST": 1482,
	 "2B - IGST": 1482,
	 "2B - Total GST": 1482,
	 "PR - IGST": 1482,
	 "PR - Total GST": 1482,
	 "2A - Invoice Date": "03\/06\/2021",
	 "PR - Invoice Date": "03\/06\/2021",
	 "QR - Invoice Date": "03\/06\/2021",
	 "2B - Invoice Date": "03\/06\/2021",
	 "2A - Invoice Number": "MHS2021000049445",
	 "2B - Invoice Number": "MHS2021000049445",
	 "QR - Invoice Number": "MHS2021000049445",
	 "PR - Invoice Number": "MHS2021000049445",
	 "QR - IRN": "967931a3ca3b170c919630a90854448877d684d86a49e8bbe005c03d26823tax",
	 "2A - Taxable": 8235,
	 "2A - Total Amount": 9717,
	 "QR - Total Amount": 9717,
	 "2B - Taxable": 8235,
	 "2B - Total Amount": 9717,
	 "PR - Taxable": 8235,
	 "PR - Total Amount": 9717,
	 "QR - Item Count": 65,
	 "QR - HSN Code": 995577,
	 "QR - NIC sign": "NIC",
	 "QR - Document Type": "INV"
	},
	{
	 "2A - Buyer GSTIN": "33AABCB3524G1Z8",
	 "PR - Buyer GSTIN": "33AABCB3524G1Z8",
	 "QR - Buyer GSTIN": "33AABCB3524G1Z8",
	 "2A - Seller GSTIN": "33AAACC4175D1Z5",
	 "PR - Seller GSTIN": "33AAACC4175D1Z5",
	 "QR - Seller GSTIN": "33AAACC4175D1Z5",
	 "2A vs PR - Total Amount Difference": 0,
	 "QR vs PR - Total Amount Difference": 0,
	 "2A vs PR - Invoice Date Mismatch": "Match",
	 "2A vs QR - Invoice Date Mismatch": "Match",
	 "QR vs PR - Invoice Date Mismatch": "Match",
	 "2A vs PR - Invoice No Mismatch": "Match",
	 "2A vs QR - Invoice No Mismatch": "Match",
	 "QR vs PR - Invoice No Mismatch": "Match",
	 "QR - S3 Link": "https:\/\/qr-invoice.s3.ap-south-1.amazonaws.com\/CHA%20Invoices\/2587.pdf",
	 "QR - Page Link": "https:\/\/s3-ap-south-1.amazonaws.com\/finkraftfiles\/March21-5-83.jpg",
	 "2A - IGST": 384,
	 "2A - Total GST": 384,
	 "PR - IGST": 384,
	 "PR - Total GST": 384,
	 "2A - Invoice Date": "03\/07\/2021",
	 "PR - Invoice Date": "03\/07\/2021",
	 "QR - Invoice Date": "03\/07\/2021",
	 "2A - Invoice Number": "TNS2021000026066",
	 "QR - Invoice Number": "TNS2021000026066",
	 "PR - Invoice Number": "TNS2021000026066",
	 "QR - IRN": "929207e9b7017c88c03ba299085ac1d28dccb80270d612912003cb1c4cca641",
	 "2A - Taxable": 2139,
	 "2A - Total Amount": 2523,
	 "QR - Total Amount": 2523,
	 "2B - Taxable": 1,
	 "2B - Total Amount": 0,
	 "PR - Taxable": 2139,
	 "PR - Total Amount": 2523,
	 "QR - Item Count": 4,
	 "QR - HSN Code": 995577,
	 "QR - NIC sign": "NIC",
	 "QR - Document Type": "INV"
	}
   ]